ocm.py
python_ocm-0.0.5.dist-info/LICENSE
python_ocm-0.0.5.dist-info/METADATA
python_ocm-0.0.5.dist-info/WHEEL
python_ocm-0.0.5.dist-info/entry_points.txt
python_ocm-0.0.5.dist-info/top_level.txt
python_ocm-0.0.5.dist-info/RECORD
