Metadata-Version: 2.1
Name: python-ocm
Version: 0.0.5
Summary: object command mapper: Python library for map command line software to Python object.
Home-page: https://github.com/soultoolman/ocm
Author: soultoolman
Author-email: soultooman@gmail.com
License: MIT
Platform: UNKNOWN
Classifier: License :: OSI Approved :: MIT License
Classifier: Programming Language :: Python
Classifier: Programming Language :: Python :: 3
Classifier: Programming Language :: Python :: 3.6
Classifier: Programming Language :: Python :: Implementation :: CPython
Classifier: Programming Language :: Python :: Implementation :: PyPy
Requires-Python: >=3.6.0
